sentence2vec/__init__.py
sentence2vec/model.py
sentence2vec/tools.py
sentence2vec/transform.py
sentence2vec-0.0.1.dist-info/LICENSE
sentence2vec-0.0.1.dist-info/METADATA
sentence2vec-0.0.1.dist-info/WHEEL
sentence2vec-0.0.1.dist-info/top_level.txt
sentence2vec-0.0.1.dist-info/RECORD
