Metadata-Version: 2.1
Name: sentence2vec
Version: 0.0.1
Summary: an elegant sentence2vec
Home-page: https://github.com/DengBoCong/sentence2vec
Author: DengBoCong
Author-email: bocongdeng@gmail.com
License: MIT License
Platform: UNKNOWN
Classifier: Programming Language :: Python :: 3
Classifier: License :: OSI Approved :: MIT License
Classifier: Operating System :: OS Independent
Requires-Dist: scikit-learn (>=0.23.2)
Requires-Dist: numpy (>=1.19.2)
